setup.py
sj_util/clarity_cli.py
sj_util/clarity_rest.py
sj_util/conall_cli.py
sj_util/marker_cli.py
sj_util/helpers/decorators.py
sj_util/helpers/job_trace.py
sj_util/helpers/utils.py
utils_cli_sjain02.egg-info/PKG-INFO
utils_cli_sjain02.egg-info/SOURCES.txt
utils_cli_sjain02.egg-info/dependency_links.txt
utils_cli_sjain02.egg-info/entry_points.txt
utils_cli_sjain02.egg-info/requires.txt
utils_cli_sjain02.egg-info/top_level.txt